Metadata-Version: 2.1
Name: vestory
Version: 1.0.1
Summary: Vestory, um controle de versões prático e rápido usado em qualquer terminal por linha de comando.
Home-page: UNKNOWN
Author: Jaedson Silva
Author-email: imunknowuser@protonmail.com
License: GNU General Public License v3.0
Project-URL: Código fonte, https://github.com/jaedsonpys/vestory
Project-URL: Licença, https://github.com/jaedsonpys/vestory/blob/master/LICENSE
Platform: UNKNOWN
